tyrian_sphinx_theme/__init__.py
tyrian_sphinx_theme/layout.html
tyrian_sphinx_theme/localtoc.html
tyrian_sphinx_theme/support.py
tyrian_sphinx_theme/theme.conf
tyrian_sphinx_theme/static/custom.css
tyrian_sphinx_theme/static/tyrian-sphinx-theme.css_t
tyrian_sphinx_theme-0.0.9.dist-info/entry_points.txt
tyrian_sphinx_theme-0.0.9.dist-info/WHEEL
tyrian_sphinx_theme-0.0.9.dist-info/METADATA
tyrian_sphinx_theme-0.0.9.dist-info/RECORD
