Metadata-Version: 2.3
Name: tyrian-sphinx-theme
Version: 0.0.9
Summary: A Tyrian based Sphinx theme for Gentoo
Author-email: Max Magorsch <max@magorsch.de>
Requires-Python: >=3.8
Classifier: Framework :: Sphinx
Classifier: Framework :: Sphinx :: Theme
Classifier: Operating System :: OS Independent
Classifier: License :: OSI Approved :: BSD License
Classifier: Programming Language :: Python :: 3
Requires-Dist: sphinx
Project-URL: Homepage, https://gitweb.gentoo.org/proj/tyrian-sphinx-theme.git
